Metadata-Version: 2.1
Name: hashbrowns
Version: 1.1
Summary: A package for cryptography in python with unique functions
Author: Cooper ransom
Author-email: Cooperransom08@outlook.com
Keywords: python,crypto,cryptograpgy,rsa,hashing-algo
Classifier: Development Status :: 3 - Alpha
Classifier: Intended Audience :: Education
Classifier: Programming Language :: Python :: 3
Classifier: Operating System :: Microsoft :: Windows
